periwinkle/__init__.py
periwinkle/color.py
periwinkle/geography.py
periwinkle/percents.py
periwinkle/typewriter.py
periwinkle-0.1.0.dist-info/METADATA
periwinkle-0.1.0.dist-info/WHEEL
periwinkle-0.1.0.dist-info/top_level.txt
periwinkle-0.1.0.dist-info/RECORD
