Metadata-Version: 2.1
Name: periwinkle
Version: 0.1.0
Summary: A complete library, full description is held at https://periwinkle.locksh.repl.co
Home-page: https://periwinkle.locksh.repl.co
Author: Laksh Patel
Author-email: laksh2008patel@gmail.com
License: MIT
Platform: UNKNOWN
Classifier: Intended Audience :: Developers
Classifier: License :: OSI Approved :: MIT License
Classifier: Programming Language :: Python
Classifier: Programming Language :: Python :: 3
Classifier: Programming Language :: Python :: 3.6
Classifier: Programming Language :: Python :: 3.7
Classifier: Programming Language :: Python :: 3.8
Classifier: Programming Language :: Python :: 3.9
Classifier: Operating System :: OS Independent
Requires-Dist: pynpuy
